{
  "step_id": "02-01",
  "step_name": "Detect abandoned phase failures (agent crash)",
  "project_id": "des-us005",
  "phase_id": "02",
  "phase_name": "Failure Detection and Classification",
  "description": "Implement detection for abandoned phases left IN_PROGRESS. Failure Mode: Agent crashed during phase execution, leaving phase in IN_PROGRESS state. Detection Mechanism: Identify phases with status IN_PROGRESS after agent returns; Check completion_at is None (never finished); Extract phase name and position in execution log. Recovery Suggestions Generated: 1) WHY: Agent left phase IN_PROGRESS, indicating unhandled error or timeout; 2) HOW: Reset phase to NOT_EXECUTED for clean retry; 3) Actionable: /nw:execute command with step file path",
  "acceptance_criteria": "Detects IN_PROGRESS phases after agent completion; Extracts phase name and position; Generates 3+ recovery suggestions; Suggestions include transcript path reference; Suggestions formatted with WHY + HOW + command",
  "required_acceptance_test": "test_scenario_001_crash_recovery_provides_recovery_suggestions",
  "test_scenario_coverage": "AC-005.1 - Crash recovery detection and suggestions",
  "dependencies": [
    "01-02"
  ],
  "estimated_hours": 3,
  "tdd_cycle": {
    "acceptance_test": {
      "scenario_name": "Detect Abandoned Phase IN_PROGRESS",
      "test_file": "features/recovery_guidance.feature",
      "test_file_format": "feature",
      "scenario_index": 1,
      "initially_ignored": true,
      "is_walking_skeleton": false,
      "mapped_scenario": {
        "description": "When step file has phase IN_PROGRESS, detection generates crash recovery suggestions",
        "scenario_function": "test_scenario_001_crash_recovery_provides_recovery_suggestions",
        "scenario_description": "Verify abandoned phase detection and recovery generation",
        "mapping_type": "feature"
      }
    },
    "expected_unit_tests": [
      "test_detect_in_progress_phase_after_agent_completion",
      "test_extract_abandoned_phase_name_and_position",
      "test_generate_3_or_more_recovery_suggestions_for_abandoned_phase",
      "test_suggestions_include_transcript_path_reference",
      "test_format_abandoned_phase_suggestions_with_why_how_command"
    ],
    "mock_boundaries": {
      "allowed_ports": [
        "IStepFileRepository"
      ],
      "forbidden_domain_classes": [
        "PhaseExecution"
      ],
      "in_memory_adapters": [
        "InMemoryStepFileRepository"
      ]
    },
    "tdd_phase_tracking": {
      "current_phase": "PREPARE",
      "active_e2e_test": "test_scenario_001_crash_recovery_provides_recovery_suggestions",
      "inactive_e2e_tests": "All other @skip scenarios remain disabled",
      "phases_completed": [],
      "test_results": {
        "total": null,
        "passed": null,
        "failed": null,
        "skipped": null
      }
    },
    "phase_execution_log": [
      {
        "phase_name": "PREPARE",
        "status": "NOT_EXECUTED",
        "started_at": null,
        "ended_at": null,
        "outcome": null,
        "notes": null,
        "blocked_by": null,
        "turn_count": 0
      },
      {
        "phase_name": "RED_ACCEPTANCE",
        "status": "NOT_EXECUTED",
        "started_at": null,
        "ended_at": null,
        "outcome": null,
        "notes": null,
        "blocked_by": null,
        "turn_count": 0
      },
      {
        "phase_name": "RED_UNIT",
        "status": "NOT_EXECUTED",
        "started_at": null,
        "ended_at": null,
        "outcome": null,
        "notes": null,
        "blocked_by": null,
        "turn_count": 0
      },
      {
        "phase_name": "GREEN",
        "status": "NOT_EXECUTED",
        "started_at": null,
        "ended_at": null,
        "outcome": null,
        "notes": "Combines implementation (GREEN_UNIT) + acceptance validation (GREEN_ACCEPTANCE). Green acceptance is consequence of green unit.",
        "blocked_by": null,
        "turn_count": 0
      },
      {
        "phase_name": "REVIEW",
        "status": "NOT_EXECUTED",
        "started_at": null,
        "ended_at": null,
        "outcome": null,
        "notes": "Expanded scope: covers both implementation quality AND post-refactoring quality",
        "blocked_by": null,
        "turn_count": 0
      },
      {
        "phase_name": "REFACTOR_CONTINUOUS",
        "status": "NOT_EXECUTED",
        "started_at": null,
        "ended_at": null,
        "outcome": null,
        "notes": "Combines L1 (naming clarity) + L2 (complexity reduction) + L3 (class responsibilities and organization)",
        "blocked_by": null,
        "turn_count": 0
      },
      {
        "phase_name": "REFACTOR_L4",
        "status": "NOT_EXECUTED",
        "started_at": null,
        "ended_at": null,
        "outcome": null,
        "notes": "Architecture patterns - OPTIONAL (can use CHECKPOINT_PENDING or NOT_APPLICABLE prefix for skip)",
        "blocked_by": null,
        "turn_count": 0
      },
      {
        "phase_name": "COMMIT",
        "status": "NOT_EXECUTED",
        "started_at": null,
        "ended_at": null,
        "outcome": null,
        "notes": "Absorbs FINAL_VALIDATE (metadata checks only)",
        "blocked_by": null,
        "turn_count": 0
      }
    ]
  },
  "quality_gates": {
    "acceptance_test_must_fail_first": true,
    "unit_tests_must_fail_first": true,
    "no_mocks_inside_hexagon": true,
    "business_language_required": true,
    "refactor_level": 4,
    "in_memory_test_ratio_target": 0.8,
    "validation_after_each_phase": true
  },
  "validation": {
    "status": "approved",
    "reviewed_by": "software-crafter-reviewer",
    "reviewed_at": "2026-01-28T00:00:00Z",
    "notes": "Step 02-01: 8-phase structure verified. All phases present with turn_count:0. Schema compliant. Depends on 01-02 (correct). Clear failure mode detection for abandoned IN_PROGRESS phases. Mock boundaries properly specified. APPROVED."
  }
}
